{"chunk_definitions":[{"chunk_id":"csetup_chunk","chunk_label":"setup","document_id":"78132BDD","expansion_state":0,"options":{"engine":"r","include":false,"label":"setup"},"row":13,"row_count":1,"visible":true},{"chunk_id":"c623z6ynmo0qp","chunk_label":"unnamed-chunk-1","document_id":"78132BDD","expansion_state":0,"options":{"engine":"r","label":"unnamed-chunk-11"},"row":68,"row_count":1,"visible":true},{"chunk_id":"c8usumdkuriq5","chunk_label":"unnamed-chunk-2","document_id":"78132BDD","expansion_state":0,"options":{"engine":"r","label":"unnamed-chunk-13"},"row":108,"row_count":1,"visible":true}],"default_chunk_options":{"echo":true,"message":false,"paged.print":true,"warning":false},"doc_write_time":1569333594,"working_dir":null}